{
    "name": "App\\Http\\Controllers\\Api\\Contracts\\Address",
    "line": 3,
    "short_desc": "",
    "long_desc": "",
    "hint": null,
    "tags": [],
    "namespace": "App\\Http\\Controllers\\Api\\Contracts",
    "file": "app\/Http\/Controllers\/Api\/Contracts\/Address.php",
    "relative_file": null,
    "hash": "b3f4b0e76c057aa99284781739e080dcc3f35048",
    "parent": null,
    "modifiers": "Stmt_Interface",
    "is_trait": false,
    "is_interface": true,
    "aliases": [],
    "errors": [],
    "interfaces": [],
    "traits": [],
    "properties": [],
    "methods": {
        "add": {
            "name": "add",
            "line": 8,
            "short_desc": "Add new address",
            "long_desc": "",
            "hint": null,
            "hint_desc": null,
            "tags": [],
            "modifiers": "1",
            "is_by_ref": "",
            "exceptions": [],
            "errors": [],
            "parameters": []
        },
        "get": {
            "name": "get",
            "line": 15,
            "short_desc": "Get all customer address",
            "long_desc": "",
            "hint": [
                [
                    "\\App\\Http\\Controllers\\Api\\Contracts\\json",
                    false
                ]
            ],
            "hint_desc": "",
            "tags": [],
            "modifiers": "1",
            "is_by_ref": "",
            "exceptions": [],
            "errors": [],
            "parameters": {
                "transformer": {
                    "name": "transformer",
                    "line": 15,
                    "short_desc": null,
                    "long_desc": null,
                    "hint": [
                        [
                            "App\\Http\\Controllers\\Api\\Contracts\\AddressTransformer",
                            false
                        ]
                    ],
                    "tags": [],
                    "modifiers": "AddressTransformer",
                    "default": null,
                    "is_by_ref": false
                }
            }
        },
        "update": {
            "name": "update",
            "line": 22,
            "short_desc": "Update customer address",
            "long_desc": "",
            "hint": [
                [
                    "\\App\\Http\\Controllers\\Api\\Contracts\\json",
                    false
                ]
            ],
            "hint_desc": "",
            "tags": [],
            "modifiers": "1",
            "is_by_ref": "",
            "exceptions": [],
            "errors": [],
            "parameters": []
        },
        "delete": {
            "name": "delete",
            "line": 29,
            "short_desc": "Delete customer address",
            "long_desc": "",
            "hint": [
                [
                    "\\App\\Http\\Controllers\\Api\\Contracts\\json",
                    false
                ]
            ],
            "hint_desc": "",
            "tags": [],
            "modifiers": "1",
            "is_by_ref": "",
            "exceptions": [],
            "errors": [],
            "parameters": []
        }
    },
    "constants": []
}